.gitignore
HISTORY.txt
Makefile
README.rst
bootstrap.py
buildout.cfg
setup.py
robotentrypoints/__init__.py
robotentrypoints/scripts.py
robotentrypoints.egg-info/PKG-INFO
robotentrypoints.egg-info/SOURCES.txt
robotentrypoints.egg-info/dependency_links.txt
robotentrypoints.egg-info/entry_points.txt
robotentrypoints.egg-info/not-zip-safe
robotentrypoints.egg-info/requires.txt
robotentrypoints.egg-info/top_level.txt