Metadata-Version: 1.0
Name: robotentrypoints
Version: 0.1
Summary: Entry points for Robot Framework
Home-page: https://github.com/gotcha/robotentrypoints
Author: Godefroid Chapelle
Author-email: gotcha@bubblenet.be
License: Apache License 2.0
Platform: UNKNOWN
